robologger/__init__.py
robologger/classes.py
robologger/loggers/base_logger.py
robologger/loggers/generic_logger.py
robologger/loggers/main_logger.py
robologger/loggers/robot_ctrl_logger.py
robologger/loggers/sensor_logger.py
robologger/loggers/video_logger.py
robologger/scripts/aggregate_data.py
robologger/scripts/interpolate_raw_robologger_data.py
robologger/scripts/merge_videos.py
robologger/scripts/rerun_visualization/base_visualizer.py
robologger/scripts/rerun_visualization/rerun_visualizer.py
robologger/scripts/rerun_visualization/visualize_robologger_episode.py
robologger/utils/color_convert.py
robologger/utils/data_aggregator.py
robologger/utils/huecodec.py
robologger/utils/stdout_setup.py
robologger/visualize/__init__.py
robologger-0.1.6.dist-info/METADATA
robologger-0.1.6.dist-info/WHEEL
robologger-0.1.6.dist-info/entry_points.txt
robologger-0.1.6.dist-info/top_level.txt
robologger-0.1.6.dist-info/RECORD
