Metadata-Version: 2.4
Name: robologger
Version: 0.1.6
Author-email: Yihuai Gao <yihuai@stanford.edu>, Jinyun Liu <jeffliu0@stanford.edu>
Project-URL: Homepage, https://github.com/yihuai-gao/robologger
Requires-Python: >=3.8
Requires-Dist: numpy
Requires-Dist: zarr<3.0.0,>=2.16.0
Requires-Dist: loguru
Requires-Dist: robotmq
Requires-Dist: robot-utils
